{
  "id": 106702460,
  "title": "Bán căn 2N1VS, 60m2 Full nội thất, View thoáng, chỉ 3.65 tỷ VHOCP",
  "description": "* Thông tin mô tả:\n+ Diện tích: 60m2\n+ Thiết kế: 2 phòng ngủ, 1 nhà vệ sinh, phòng khách, bếp, ban công, lô gia...\n+ Pháp lý: Sổ đỏ chính chủ\n+ Full nội thất\n+ View thoáng đẹp vĩnh viễn không bị che chắn\n+ Giá bán: 3.65 tỷ (Giá chưa gồm thuế phí)\n* Tiện ích:\n+ Được hưởng free toàn bộ tiện ích: Bể bơi bốn mùa, ngoài trời, sân chơi trẻ em, sân thể thao bóng đá, bóng bàn, bóng rổ, cầu lông, tenis,...\n+ Cực kỳ thuận tiện cho các cháu bé đi học trong khu, dễ dàng đăng ký các suất học mới.\n+ Liên hệ ngay hoặc nhắn ZALO cho em để xem nhà trực tiếp: ( Xem nhà 24/7)",
  "price": 3650000000,
  "area_m2": 123,
  "price_per_m2": 29674796.747967478,
  "region": "Hà Nội",
  "district": "Huyện Gia Lâm",
  "ward": "Thị trấn Trâu Quỳ",
  "street": "Yên Viên",
  "lat": 21.02097,
  "lng": 105.93817,
  "property_type": null,
  "category": 1010,
  "post_time": 1765506961000,
  "images": 12
}