{
  "id": 129329009,
  "title": "BÁN CHUNG CƯ V1 ĐÔNG TÁC, CHÙA BỘC Ở NGAY, OTO ĐỖ CỬA, FULL ĐỒ 1-2PN",
  "description": "Mở Bán - Chung cư V1 Đông Tác  - chùa Bộc 36 - 55m, Full Nội Thất, Ở ngay Tặng Vàng 24k.\n✔️ Gần các tuyến đường trung tâm: Đong Tác, chùa Bộc, Tôn Thất Tùng...\n✔️ Gần các trường c1, c2, đại học lớn: Y dược, Bách Khoa, Xây Dựng, KTQD...\n✔️Diện tích:  26m2 ; 35m2 ; 40m2 ; 50m2 ; 55m2 ; 60m2\n✔️Giá bán: Từ 900tr ; 1060tr ; 1160tr ; 1,3 tỷ hơn 1.5 tỷ \n✔️ CHIẾT KHẤU GIẢM GIÁ NGAY 50 TRIỆU MỖI CĂN. \n✔️ Quy mô và thiết kế: Gồm 6 tầng căn hộ, mỗi tầng 4-5 căn, rộng thoáng, tầng 1 để xe.\n✔️ Tòa nhà được trang bị 1 thang máy tốc độ cao, bảo vệ trực 24/24, PCCC hiện đại.\n✔️ Giá bán đã bao gồm chi phí làm sổ và nội thất căn hộ.\n✔️ Nội thất: Tủ bếp trên dưới, bếp từ, hút mùi, thiết bị vệ sinh, bình nóng lạnh, đầu chờ internet, điều hòa., giường tủ, kệ ti vi, sàn gỗ, trần thạch cao\n✔️Liên hệ chủ đầu tư: *** (tôi là chủ).\n✔️ Xem nhà 24/24 - Có tư Vấn Zalo",
  "price": 900000000,
  "area_m2": 75,
  "price_per_m2": 12000000.0,
  "region": "Hà Nội",
  "district": "Quận Đống Đa",
  "ward": "Phường Kim Liên",
  "street": "Phố Đông Tác",
  "lat": 21.005917,
  "lng": 105.834045,
  "property_type": null,
  "category": 1010,
  "post_time": 1765510338000,
  "images": 9
}