{
  "id": 129624222,
  "title": "NHỈNH 9 TỶ DÒNG TIỀN ĐỐNG ĐA- NHÀ MỚI - NGÕ NÔNG- BA GÁC",
  "description": "Mô tả chi tiết\nNGÕ NÔNG RỘNG 5M - XE 3 GÁC ĐỖ CỬA - DÒNG TIỀN SẴN\n+ Vị trí cực hiếm: Ngõ nông – rộng – thoáng, ba gác vào tận cửa, vài bước ra Xã Đàn & Trung Phụng.\n+ Trước nhà rộng 5m: Quay đầu xe dễ dàng, không bị chắn hay bí. DT sân chung 11m2.\n+ Nhà đẹp – công năng đầy đủ: 5 tầng, 6 ngủ, 4 wc; tầng 1 khách + bếp; tầng 5 sân phơi + tiểu cảnh.\n+ Dòng tiền tốt: Đang cho thuê gần 20tr/tháng.\n+ Pháp lý chuẩn: Sổ đỏ vuông đẹp, sẵn",
  "price": 9600000000,
  "area_m2": 75,
  "price_per_m2": 128000000.0,
  "region": "Hà Nội",
  "district": "Quận Đống Đa",
  "ward": "Phường Thổ Quan",
  "street": "Đê La Thành Nhỏ",
  "lat": 21.016975,
  "lng": 105.83417,
  "property_type": null,
  "category": 1020,
  "post_time": 1765506241000,
  "images": 8
}