{
  "id": 129622762,
  "title": "Bán biệt thự 3 tầng 3 mặt thoáng cầu giấy, xe lexus đỗ tại cửa",
  "description": "Nằm trong phố cầu giấy căn nhà 3 tầng 3 mặt thoáng hiếm gặp\nDiện tích lớn mặt tiền rộng đẹp\nÔ tô đỗ tại cửa\nKhu phân lô của cán bộ công an\nDân trí cao an ninh cực tốt\nNằm ở vị trí trung tâm thuận tiện đi các ngả\nSổ vuông đẹp sẵn sàng giao dịch ngay\nLiên hệ em hưng để được hỗ trợ ***",
  "price": 23880000000,
  "area_m2": 79,
  "price_per_m2": 302278481.01265824,
  "region": "Hà Nội",
  "district": "Quận Cầu Giấy",
  "ward": "Phường Quan Hoa",
  "street": "Đường Cầu Giấy",
  "lat": 21.030447,
  "lng": 105.8012,
  "property_type": null,
  "category": 1020,
  "post_time": 1765503723000,
  "images": 3
}